MANIFEST.in
setup.cfg
setup.py
docs/HISTORY.txt
docs/LICENSE.GPL
docs/LICENSE.txt
src/collective/__init__.py
src/collective.caching.hostname.egg-info/PKG-INFO
src/collective.caching.hostname.egg-info/SOURCES.txt
src/collective.caching.hostname.egg-info/dependency_links.txt
src/collective.caching.hostname.egg-info/entry_points.txt
src/collective.caching.hostname.egg-info/namespace_packages.txt
src/collective.caching.hostname.egg-info/not-zip-safe
src/collective.caching.hostname.egg-info/requires.txt
src/collective.caching.hostname.egg-info/top_level.txt
src/collective/caching/__init__.py
src/collective/caching/hostname/__init__.py
src/collective/caching/hostname/setuphandlers.py
src/collective/caching/hostname/testing.py
src/collective/caching/hostname/operations/__init__.py
src/collective/caching/hostname/operations/default.py
src/collective/caching/hostname/operations/utils.py
src/collective/caching/hostname/tests/__init__.py
src/collective/caching/hostname/tests/test_operations.py
src/collective/caching/hostname/tests/test_setup.py
src/collective/caching/hostname/upgrades/__init__.py
src/collective/caching/hostname/upgrades/to1000.py