Metadata-Version: 1.0
Name: collective.caching.hostname
Version: 0.5
Summary: Hostname based blacklist caching operations for Plone
Home-page: http://www.simplesconsultoria.com.br
Author: Simples Consultoria
Author-email: products@simplesconsultoria.com.br
License: gpl
Keywords: python plone zope simples_consultoria
Platform: UNKNOWN
Classifier: Framework :: Plone
Classifier: Framework :: Plone :: 4.1
Classifier: Framework :: Plone :: 4.2
Classifier: Framework :: Zope2
Classifier: Framework :: Zope3
Classifier: Programming Language :: Python
Classifier: Topic :: Internet :: WWW/HTTP
Classifier: Topic :: Internet :: WWW/HTTP :: Dynamic Content
Classifier: Topic :: Software Development :: Libraries :: Python Modules
